contextlite/__init__.py
contextlite/__main__.py
contextlite/binary_manager.py
contextlite/client.py
contextlite/exceptions.py
contextlite/py.typed
contextlite-2.0.7.dist-info/METADATA
contextlite-2.0.7.dist-info/WHEEL
contextlite-2.0.7.dist-info/entry_points.txt
contextlite-2.0.7.dist-info/top_level.txt
contextlite-2.0.7.dist-info/RECORD
