Metadata-Version: 2.1
Name: contextlite
Version: 2.0.7
Summary: RAG Systems Were a Mistake - Replace vector databases with 0.3ms mathematically optimal context selection
Author-email: ContextLite Team <support@contextlite.com>
License: MIT
Project-URL: Homepage, https://contextlite.com
Project-URL: Documentation, https://docs.contextlite.com
Project-URL: Repository, https://github.com/Michael-A-Kuykendall/contextlite
Project-URL: Bug Reports, https://github.com/Michael-A-Kuykendall/contextlite/issues
Project-URL: Changelog, https://github.com/Michael-A-Kuykendall/contextlite/releases
Keywords: rag,vector-database-alternative,smt-optimization,context-engine,ai,retrieval,fast,local,zero-cost,optimal
Classifier: Development Status :: 5 - Production/Stable
Classifier: Intended Audience :: Developers
Classifier: License :: OSI Approved :: MIT License
Classifier: Operating System :: OS Independent
Classifier: Programming Language :: Python :: 3
Classifier: Programming Language :: Python :: 3.8
Classifier: Programming Language :: Python :: 3.9
Classifier: Programming Language :: Python :: 3.10
Classifier: Programming Language :: Python :: 3.11
Classifier: Programming Language :: Python :: 3.12
Classifier: Topic :: Database
Classifier: Topic :: Scientific/Engineering :: Artificial Intelligence
Classifier: Topic :: Software Development :: Libraries :: Python Modules
Classifier: Topic :: Text Processing :: Indexing
Requires-Python: >=3.8
Requires-Dist: requests>=2.25.0
Requires-Dist: platformdirs>=2.0.0
Provides-Extra: dev
Requires-Dist: pytest>=6.0; extra == "dev"
Requires-Dist: pytest-cov; extra == "dev"
Requires-Dist: black; extra == "dev"
Requires-Dist: isort; extra == "dev"
Requires-Dist: mypy; extra == "dev"
